cyberflySdk/__init__.py
cyberflySdk/api.py
cyberflySdk/auth.py
cyberflySdk/config.py
cyberflySdk/main.py
cyberflySdk/utils.py
cyberfly_client_sdk-0.1.dist-info/LICENSE
cyberfly_client_sdk-0.1.dist-info/METADATA
cyberfly_client_sdk-0.1.dist-info/WHEEL
cyberfly_client_sdk-0.1.dist-info/top_level.txt
cyberfly_client_sdk-0.1.dist-info/RECORD
