Metadata-Version: 2.1
Name: cyberfly-client-sdk
Version: 0.1
Summary: UNKNOWN
Home-page: https://github.com/cyberfly-io/cyberfly-python-client-sdk
License: UNKNOWN
Platform: UNKNOWN
License-File: LICENSE
Requires-Dist: requests
Requires-Dist: pypact-lang
Requires-Dist: rule-engine
Requires-Dist: python-socketio[client]
